MeerKATgen/__init__.py
MeerKATgen/create_dataset.py
MeerKATgen/observation.py
MeerKATgen/sim_params.py
MeerKATgen/utils.py
MeerKATgen/visualizations.py
MeerKATgen-0.0.2.dist-info/METADATA
MeerKATgen-0.0.2.dist-info/WHEEL
MeerKATgen-0.0.2.dist-info/top_level.txt
MeerKATgen-0.0.2.dist-info/RECORD
